Workbook
Name aporte: Planilha1!$D$16:$D$16
Name patrimonio: Planilha1!$D$19:$D$19
Name periodo_investimento: Planilha1!$D$17:$D$17
Name rendimento_carteira: Planilha1!$D$11:$D$11
Name salario: Planilha1!$D$10:$D$10
Name sugestao_investimento: Planilha1!$D$12:$D$12

Sheet Planilha1
F2: TIPO DE FII | G2: PERCENTUAL SUGERIDO | H2: VALORES
F3: PAPEL | G3: =VLOOKUP($D$13&"-"&F3,Planilha2!$A$2:$D$20,4,FALSE) -> 0.3 | H3: {=G3*aporte} -> 750
F4: TIJOLO | G4: =VLOOKUP($D$13&"-"&F4,Planilha2!$A$2:$D$20,4,FALSE) -> 0.5 | H4: {=G4*aporte} -> 1250
F5: HÍBRIDOS | G5: =VLOOKUP($D$13&"-"&F5,Planilha2!$A$2:$D$20,4,FALSE) -> 0.1 | H5: {=G5*aporte} -> 250
F6: FOFs | G6: =VLOOKUP($D$13&"-"&F6,Planilha2!$A$2:$D$20,4,FALSE) -> 0.1 | H6: {=G6*aporte} -> 250
F7: DESENVOLVIMENTO | G7: =VLOOKUP($D$13&"-"&F7,Planilha2!$A$2:$D$20,4,FALSE) -> 0 | H7: {=G7*aporte} -> 0
F8: HOTELARIAS | G8: =VLOOKUP($D$13&"-"&F8,Planilha2!$A$2:$D$20,4,FALSE) -> 0 | H8: {=G8*aporte} -> 0
B9: CONFIGURAÇÕES | F9: TOTAL | H9: =SUM(H3:H8) -> 2500
B10: Salário | D10: 3900
B11: Rendimento da Carteira de Investimentos | D11: 0.0089
B12: Sugestão de Investimento | D12: =D10*30% -> 1170
B13: Perfil de Investidor | D13: CONSERVADOR
B15: INVESTIMENTO MENSAL | F15: CENÁRIOS | H15: DIVIDENDOS
B16: Quanto investir por mes: | D16: 2500 | F16: 2 Anos: | G16: {=FV(rendimento_carteira,$A28*12,aporte*-1)} -> 66561.216 | H16: {=G16*rendimento_carteira} -> 592.39482
B17: Por quantos anos: | D17: 5 | F17: 5 Anos: | G17: {=FV(rendimento_carteira,$A29*12,aporte*-1)} -> 197111.5 | H17: {=G17*rendimento_carteira} -> 1754.2923
B18: Taxa de rendimento mensal: | D18: 0.01079 | F18: 10 Anos: | G18: {=FV(rendimento_carteira,$A30*12,aporte*-1)} -> 532539.48 | H18: {=G18*rendimento_carteira} -> 4739.6014
B19: Patrimônio acumulado: | D19: {=FV(D18,periodo_investimento*12,aporte*-1)} -> 209442.28 | F19: 20 Anos: | G19: {=FV(rendimento_carteira,$A31*12,aporte*-1)} -> 2074688.9 | H19: {=G19*rendimento_carteira} -> 18464.731
B20: Dividendos mensais: | D20: {=patrimonio*rendimento_carteira} -> 1864.0363 | F20: 30 Anos: | G20: {=FV(rendimento_carteira,$A32*12,aporte*-1)} -> 6540507.7 | H20: {=G20*rendimento_carteira} -> 58210.518
A28: 2
A29: 5
A30: 10
A31: 20
A32: 30

Sheet Planilha2
A2: CHAVE | B2: PERFIL | C2: TIPO DE FII | D2: %
A3: =B3&"-"&C3 -> CONSERVADOR-PAPEL | B3: CONSERVADOR | C3: PAPEL | D3: 0.3
A4: =B4&"-"&C4 -> CONSERVADOR-TIJOLO | B4: CONSERVADOR | C4: TIJOLO | D4: 0.5
A5: =B5&"-"&C5 -> CONSERVADOR-HÍBRIDOS | B5: CONSERVADOR | C5: HÍBRIDOS | D5: 0.1
A6: =B6&"-"&C6 -> CONSERVADOR-FOFs | B6: CONSERVADOR | C6: FOFs | D6: 0.1
A7: =B7&"-"&C7 -> CONSERVADOR-DESENVOLVIMENTO | B7: CONSERVADOR | C7: DESENVOLVIMENTO | D7: 0
A8: =B8&"-"&C8 -> CONSERVADOR-HOTELARIAS | B8: CONSERVADOR | C8: HOTELARIAS | D8: 0
A9: =B9&"-"&C9 -> MODERADO-PAPEL | B9: MODERADO | C9: PAPEL | D9: 0.35
A10: =B10&"-"&C10 -> MODERADO-TIJOLO | B10: MODERADO | C10: TIJOLO | D10: 0.35
A11: =B11&"-"&C11 -> MODERADO-HÍBRIDOS | B11: MODERADO | C11: HÍBRIDOS | D11: 0.1
A12: =B12&"-"&C12 -> MODERADO-FOFs | B12: MODERADO | C12: FOFs | D12: 0.1
A13: =B13&"-"&C13 -> MODERADO-DESENVOLVIMENTO | B13: MODERADO | C13: DESENVOLVIMENTO | D13: 0.05
A14: =B14&"-"&C14 -> MODERADO-HOTELARIAS | B14: MODERADO | C14: HOTELARIAS | D14: 0.05
... A20: =B20&"-"&C20 -> AGRESSIVO-HOTELARIAS | B20: AGRESSIVO | C20: HOTELARIAS | D20: 0.1
